{
    " ": 808834,
    "e": 468686,
    "t": 342755,
    "a": 315678,
    "o": 291130,
    "i": 278560,
    "n": 272234,
    "s": 251496,
    "r": 236388,
    "h": 177438,
    "l": 159533,
    "d": 140966,
    "e ": 137693,
    "c": 118289,
    "u": 107057,
    " t": 95049,
    "m": 92463,
    "s ": 80339,
    "f": 79247,
    "p": 78983,
    "g": 78495,
    "in": 74180,
    "y": 68152,
    "w": 64778,
    " th": 62968,
    "er": 60538,
    "t ": 59761,
    "an": 56707,
    "d ": 54818,
    "b": 54204,
    "on": 49248,
    ".": 45206,
    ",": 43589,
    "\n": 42082,
    "en": 41346,
    "v": 40713,
    "or": 38866,
    " the ": 38400,
    ", ": 35702,
    "y ": 35167,
    "ar": 32358,
    "at": 31070,
    "o ": 30854,
    "al": 30815,
    "ou": 29876,
    "k": 29802,
    "re": 29155,
    "ing": 28625,
    "it": 26887,
    "of": 24175,
    ". ": 23966,
    "st": 23910,
    "\n\n": 22179,
    "a ": 21882,
    "ic": 19899,
    "ed ": 18719,
    "and ": 18060,
    "ing ": 17716,
    "om": 17388,
    "th": 17383,
    "es": 17044,
    "T": 16734,
    "ion": 16705,
    " to ": 16191,
    "er ": 15886,
    "il": 14881,
    "is ": 14708,
    "ac": 14408,
    "of ": 14405,
    "el": 14306,
    "I": 14181,
    "S": 13959,
    "A": 13358,
    "ha": 13337,
    "is": 13078,
    "ed": 13019,
    "in ": 12276,
    "as": 12170,
    "for": 12140,
    "h ": 12138,
    ".\n\n": 11812,
    "-": 11635,
    "es ": 11544,
    "ec": 11363,
    "ro": 11198,
    "at ": 11047,
    "C": 10790,
    "an ": 10407,
    "0": 10366,
    "ol": 10173,
    "ow": 10030,
    "ent": 9689,
    "am": 9646,
    "he ": 9638,
    "al ": 9506,
    "1": 9420,
    "im": 9389,
    "em": 9226,
    "us": 9155,
    "id": 9146,
    "as ": 8984,
    "ig": 8915,
    "M": 8809,
    "pl": 8733,
    "\u2019": 8720,
    "ve ": 8716,
    "wh": 8610,
    "ur": 8507,
    "x": 8469,
    "l ": 8305,
    "en ": 7907,
    "et": 7883,
    "B": 7881,
    "ir": 7870,
    "ad": 7783,
    "un": 7522,
    "ion ": 7277,
    "P": 7263,
    "ly ": 7223,
    "2": 7136,
    "ag": 6884,
    "ver": 6864,
    "le": 6807,
    "on ": 6802,
    "ch": 6792,
    "ab": 6772,
    "W": 6707,
    " that ": 6639,
    "\"": 6596,
    "os": 6569,
    "wit": 6550,
    "'": 6539,
    "k ": 6486,
    "E": 6477,
    "e th": 6346,
    "R": 6309,
    "D": 6233,
    "ay": 6111,
    "and": 5957,
    "H": 5939,
    "F": 5934,
    "N": 5791,
    "for ": 5722,
    "con": 5698,
    "ent ": 5599,
    "The ": 5599,
    "ex": 5456,
    "com": 5439,
    "you": 5336,
    "it ": 5316,
    "su": 5287,
    "O": 5084,
    "ear": 5063,
    "op": 5056,
    "pro": 5049,
    "L": 4968,
    "li": 4939,
    "j": 4932,
    "fr": 4924,
    "e t": 4913,
    "n ": 4901,
    "of the ": 4877,
    "be": 4837,
    "res": 4826,
    "or ": 4823,
    "no": 4819,
    "ut": 4726,
    "G": 4717,
    ":": 4693,
    "int": 4674,
    "\u2019s ": 4670,
    "ap": 4652,
    "ul": 4587,
    "ri": 4523,
    "sh": 4450,
    ")": 4416,
    "oo": 4379,
    "(": 4345,
    "was ": 4320,
    " the": 4207,
    "se": 4204,
    "oun": 4186,
    "ak": 4186,
    "are ": 4185,
    "s, ": 4180,
    "I ": 4177,
    "with ": 4098,
    "de": 4065,
    "igh": 4046,
    "\u201c": 4036,
    "if": 4030,
    "be ": 4009,
    "\u201d": 4002,
    "ere ": 4001,
    "ne": 3990,
    "in the ": 3986,
    "ation": 3876,
    "our": 3851,
    "z": 3839,
    "e, ": 3822,
    "oc": 3809,
    "oul": 3795,
    " to": 3766,
    "Th": 3720,
    "bl": 3703,
    "um": 3702,
    "have ": 3681,
    "ers ": 3671,
    "3": 3627,
    "p ": 3560,
    "ay ": 3553,
    "from": 3544,
    "ect": 3531,
    "5": 3527,
    "all": 3493,
    "U": 3466,
    "q": 3391,
    "ould ": 3301,
    "uc": 3299,
    ": ": 3298,
    "ot": 3275,
    "sa": 3266,
    "ist": 3263,
    "4": 3250,
    "ill ": 3240,
    "qu": 3226,
    "wor": 3181,
    "J": 3168,
    "enc": 3161,
    "sp": 3159,
    "9": 3120,
    "act": 3118,
    "est": 3102,
    "per": 3091,
    "ation ": 3074,
    "ut ": 3055,
    "'s ": 3041,
    "iv": 3023,
    "w ": 3004,
    "cl": 2992,
    "art": 2960,
    "out ": 2951,
    "not ": 2949,
    "s. ": 2905,
    "20": 2881,
    "ir ": 2877,
    "ic ": 2862,
    "by ": 2842,
    "ant": 2811,
    "ev": 2806,
    "oth": 2791,
    "you ": 2764,
    "le ": 2740,
    "por": 2717,
    "ow ": 2715,
    "ain": 2701,
    "his ": 2691,
    "e the ": 2688,
    "e. ": 2688,
    "6": 2667,
    "has ": 2663,
    "ate ": 2595,
    " this ": 2582,
    "e to ": 2541,
    "ed to ": 2537,
    "K": 2536,
    "ive ": 2530,
    "7": 2527,
    "end": 2522,
    "we": 2509,
    "one ": 2504,
    "anc": 2494,
    "ud": 2439,
    "gr": 2427,
    "from ": 2422,
    "af": 2407,
    "ity ": 2400,
    ", the ": 2395,
    "\u201d ": 2394,
    "str": 2379,
    "rec": 2372,
    "so ": 2360,
    "8": 2342,
    "will ": 2328,
    "oug": 2323,
    "/": 2309,
    "off": 2298,
    "id ": 2289,
    "ep": 2280,
    "y, ": 2278,
    "od": 2275,
    "pr": 2268,
    "mor": 2249,
    "pe": 2242,
    "ill": 2240,
    "ong": 2224,
    "out": 2200,
    "over": 2167,
    "ally ": 2166,
    "ess": 2165,
    "ter": 2151,
    "0 ": 2140,
    "at the ": 2138,
    " tr": 2136,
    "with": 2118,
    "et ": 2083,
    "e of ": 2075,
    "all ": 2072,
    "s and ": 2063,
    "we ": 2057,
    "ing the ": 2050,
    "V": 2045,
    "ov": 2010,
    "Y": 1995,
    "ack": 1990,
    " and ": 1988,
    "av": 1978,
    "s of ": 1968,
    "year": 1960,
    "St": 1907,
    "lik": 1899,
    "ob": 1897,
    " they ": 1894,
    "?": 1871,
    " their ": 1867,
    "any ": 1864,
    ", and ": 1857,
    "som": 1857,
    "who ": 1846,
    ". I": 1844,
    "cont": 1841,
    "whic": 1833,
    "but ": 1833,
    "ar ": 1825,
    "s to ": 1824,
    "ter ": 1811,
    "form": 1787,
    "ies ": 1779,
    "he": 1776,
    "port": 1770,
    "sc": 1770,
    "inc": 1767,
    "ell": 1755,
    "ef": 1749,
    "hat ": 1748,
    "up": 1742,
    " to the ": 1738,
    ") ": 1736,
    "vi": 1732,
    "si": 1725,
    "ind": 1713,
    "can ": 1713,
    "\" ": 1711,
    "ight": 1708,
    "pos": 1708,
    "on the ": 1705,
    "our ": 1702,
    "ang": 1700,
    "201": 1697,
    "were ": 1696,
    "und": 1687,
    "est ": 1680,
    "th ": 1679,
    "would ": 1677,
    "ard": 1666,
    "which ": 1648,
    "og": 1642,
    "s.\n\n": 1633,
    "ight ": 1626,
    "fe": 1624,
    "[": 1622,
    "]": 1622,
    "ch ": 1605,
    "ass": 1601,
    "ing to ": 1593,
    "es, ": 1564,
    "ial ": 1563,
    "ice ": 1558,
    "\u2014": 1556,
    "ust ": 1555,
    ". The ": 1555,
    "ment": 1537,
    "dis": 1529,
    "pol": 1520,
    "do": 1508,
    "been ": 1502,
    "ost ": 1499,
    "ser": 1491,
    "r ": 1490,
    "ail": 1484,
    "st ": 1483,
    "mak": 1483,
    "ad ": 1481,
    "ed the ": 1479,
    "ord": 1479,
    "pres": 1475,
    "ple ": 1468,
    "bec": 1466,
    "its ": 1465,
    "f ": 1463,
    "go": 1456,
    "ast": 1454,
    "$": 1453,
    "other ": 1448,
    "had ": 1440,
    ". A": 1433,
    "ast ": 1430,
    "fir": 1428,
    "me": 1425,
    "ment ": 1423,
    "her ": 1420,
    "acc": 1417,
    "ough": 1416,
    "comp": 1412,
    "iz": 1405,
    "ame ": 1399,
    "about ": 1395,
    "m ": 1393,
    "aw": 1393,
    "said": 1392,
    "ly": 1391,
    "Wh": 1389,
    "ey ": 1384,
    "for the ": 1378,
    "att": 1377,
    "pre": 1376,
    "more ": 1375,
    "po": 1375,
    "ug": 1357,
    "peo": 1344,
    "also ": 1343,
    "di": 1342,
    "\u2019t ": 1337,
    ". Th": 1335,
    "ated ": 1334,
    "ack ": 1319,
    "ens": 1319,
    "aus": 1319,
    "In": 1318,
    "inter": 1316,
    "e.\n\n": 1304,
    "ever": 1303,
    "i ": 1290,
    "ical ": 1284,
    "br": 1280,
    "work": 1266,
    "arg": 1260,
    "her": 1260,
    "co": 1260,
    " that": 1258,
    "ign": 1257,
    "comm": 1256,
    "lin": 1250,
    "ely ": 1248,
    "and the ": 1247,
    "em ": 1236,
    "sel": 1234,
    ";": 1231,
    "fin": 1228,
    "my ": 1227,
    "own ": 1222,
    "Ch": 1217,
    "\u2013": 1216,
    "up ": 1208,
    "fer": 1204,
    "your ": 1200,
    "fl": 1199,
    "ound": 1197,
    "19": 1194,
    "min": 1189,
    "e and ": 1188,
    "el ": 1183,
    "cr": 1181,
    "us ": 1179,
    " tim": 1175,
    "=": 1165,
    "dr": 1164,
    "by": 1162,
    "ess ": 1154,
    "ure": 1154,
    "oll": 1151,
    "a l": 1149,
    "kn": 1147,
    "des": 1144,
    "sid": 1140,
    "t of ": 1125,
    "ust": 1124,
    "age ": 1121,
    "part": 1120,
    "play": 1119,
    "par": 1119,
    "ous": 1118,
    "ubl": 1117,
    "ain ": 1116,
    "ary ": 1113,
    "a s": 1111,
    "ity": 1111,
    "emb": 1110,
    "A ": 1109,
    "day": 1108,
    "ure ": 1103,
    "00": 1103,
    "ip": 1095,
    "mon": 1084,
    ". H": 1083,
    "man": 1081,
    "ount": 1079,
    "s the ": 1079,
    "eth": 1073,
    "duc": 1072,
    "say": 1068,
    "ous ": 1065,
    "him": 1065,
    "said ": 1061,
    "_": 1056,
    "ite ": 1056,
    "what ": 1053,
    "\u201d\n\n": 1049,
    "own": 1047,
    "mer": 1047,
    "rem": 1031,
    "when ": 1030,
    "ach": 1028,
    "able ": 1024,
    "An": 1024,
    "ose ": 1023,
    "most ": 1020,
    "just ": 1019,
    "with the ": 1010,
    "way": 1010,
    "ence ": 1008,
    "some ": 1007,
    "am ": 1003,
    "ions ": 1003,
    "ed by ": 1003,
    ",\u201d ": 1003,
    "--": 1002,
    "'t ": 1001,
    "not": 994,
    "like ": 992,
    "bet": 991,
    "new ": 990,
    "no ": 987,
    "dec": 984,
    "wo ": 976,
    ".\n\nThe ": 974,
    "itt": 966,
    "? ": 966,
    "ound ": 965,
    "people ": 963,
    "vers": 962,
    "ew": 961,
    "ans": 957,
    "ant ": 954,
    "ese ": 946,
    "if ": 941,
    "ph": 939,
    "ook": 936,
    "ire": 931,
    "old ": 930,
    ".\u201d\n\n": 927,
    "Tr": 923,
    "s that ": 922,
    "sec": 922,
    "|": 920,
    "ed in ": 919,
    ". B": 918,
    "reat": 918,
    "ile ": 915,
    "don": 915,
    "ong ": 913,
    "Un": 907,
    "!": 906,
    "from the ": 906,
    "e that ": 906,
    "vel": 904,
    "5 ": 902,
    "We ": 901,
    "a c": 898,
    "mar": 898,
    "ents ": 897,
    "ard ": 897,
    "ann": 893,
    "add": 890,
    "row": 888,
    "leg": 886,
    "do ": 886,
    "ook ": 883,
    "ult": 883,
    "er, ": 881,
    "ough ": 878,
    "ood ": 878,
    "reg": 876,
    "\u2013 ": 876,
    "could ": 875,
    "she ": 873,
    "but": 871,
    "x ": 869,
    "; ": 869,
    "re ": 865,
    " tak": 864,
    "prov": 863,
    "inv": 862,
    "med": 862,
    "ies": 862,
    "becaus": 861,
    ". S": 860,
    "il ": 855,
    ", th": 852,
    "only ": 850,
    "was": 850,
    "ick": 849,
    "reas": 845,
    "ict": 843,
    "bel": 841,
    "ew ": 839,
    "sup": 836,
    "get ": 836,
    "end ": 835,
    "2 ": 834,
    "bu": 832,
    "o the ": 830,
    "\"\n\n": 830,
    "serv": 828,
    "abl": 822,
    "s in ": 821,
    "sur": 817,
    "pt": 817,
    "e-": 817,
    "rat": 814,
    "ia ": 809,
    "\u2014 ": 808,
    "sy": 804,
    "a, ": 804,
    "app": 802,
    "hel": 802,
    "1 ": 802,
    "clud": 801,
    "ing, ": 801,
    "first ": 796,
    "a b": 795,
    "ans ": 795,
    "want": 794,
    "ret": 789,
    "oy": 789,
    "ish": 787,
    "pp": 785,
    "ed, ": 782,
    "a m": 781,
    "eng": 779,
    "ett": 776,
    "ell ": 767,
    "stat": 766,
    "S ": 765,
    "ek": 762,
    " that the ": 761,
    "pa": 761,
    "ory ": 758,
    "sl": 758,
    "cho": 755,
    "again": 754,
    ",\" ": 753,
    "gl": 750,
    "ial": 749,
    "ey": 749,
    "ian ": 748,
    "lat": 746,
    "ome ": 745,
    "read": 744,
    "son": 744,
    "overn": 743,
    "ot ": 743,
    "very ": 742,
    "dif": 740,
    "into ": 738,
    "urn": 738,
    "ond": 738,
    "In ": 729,
    "includ": 728,
    "after ": 727,
    "publ": 727,
    "eas": 726,
    "many ": 724,
    "under": 723,
    "eg": 721,
    "stud": 719,
    "ition": 719,
    "ect ": 717,
    "ement": 716,
    "ach ": 716,
    "old": 714,
    "offic": 712,
    "ree ": 711,
    "iss": 710,
    "olog": 708,
    "by the ": 707,
    "ance ": 707,
    "au": 706,
    "4 ": 705,
    "mat": 704,
    "ext": 702,
    "3 ": 701,
    " thin": 699,
    "ener": 696,
    "ade ": 693,
    ".\"\n\n": 693,
    "any": 689,
    "ock": 687,
    "should ": 687,
    "ere": 685,
    "being ": 684,
    "bas": 684,
    "You": 684,
    "meric": 680,
    "Al": 680,
    "plac": 679,
    "tion ": 678,
    "es and ": 677,
    "wr": 676,
    "fac": 676,
    "car": 675,
    "so": 674,
    "la": 672,
    "ident": 671,
    "back": 671,
    "Americ": 670,
    ", but ": 669,
    "ject": 667,
    "riv": 666,
    "sub": 666,
    "om ": 666,
    "chang": 665,
    "ers": 663,
    " thr": 661,
    "resp": 659,
    "ide": 659,
    "ist ": 657,
    "gu": 656,
    "cas": 655,
    " them": 654,
    "lo": 654,
    " two ": 652,
    "befor": 650,
    "a f": 650,
    "Q": 648,
    "make ": 647,
    "even ": 644,
    "\n\n\n\n": 643,
    "govern": 643,
    "Fr": 643,
    " than ": 641,
    "how ": 641,
    "count": 638,
    "ra": 637,
    "cam": 636,
    "==": 636,
    "run": 634,
    "ations ": 633,
    "may ": 629,
    "cer": 629,
    " te": 628,
    "ings ": 625,
    "ine ": 625,
    "exp": 621,
    "about": 621,
    "] ": 621,
    "day ": 620,
    "the ": 619,
    "This ": 617,
    "umb": 616,
    "- ": 616,
    "op ": 614,
    "n\u2019t ": 611,
    "call": 611,
    "ement ": 609,
    "ue ": 607,
    "es of ": 602,
    "over ": 601,
    "can": 601,
    "dat": 600,
    "es to ": 599,
    "gam": 599,
    "ing a ": 598,
    "ok": 597,
    "report": 596,
    "ort": 596,
    "ual ": 596,
    "to ": 596,
    "ik": 592,
    "struc": 590,
    "pat": 590,
    "It ": 590,
    "worl": 589,
    "ech": 588,
    "port ": 587,
    "ry ": 587,
    "ational ": 586,
    "compl": 586,
    "air": 584,
    "Com": 583,
    "org": 581,
    " there ": 581,
    "e in ": 581,
    "uch ": 580,
    "%": 578,
    "is a ": 578,
    "ept": 576,
    "um ": 576,
    "start": 576,
    "\u2019 ": 575,
    "man ": 575,
    "..": 575,
    "ed a ": 574,
    "y to ": 574,
    "is the ": 572,
    "now ": 572,
    "fi": 571,
    "betwe": 570,
    "devel": 570,
    "ank": 570,
    " them ": 570,
    "ma": 569,
    "last ": 569,
    "such ": 568,
    "On": 568,
    "en the ": 567,
    "ors ": 565,
    "rect": 563,
    "Con": 563,
    "10": 563,
    "ign ": 562,
    ". I ": 561,
    ":\n\n": 561,
    "ul ": 558,
    "cre": 556,
    "ood": 555,
    "lif": 555,
    "as a ": 554,
    "Ar": 553,
    "where ": 551,
    "ver ": 551,
    "cur": 551,
    "because ": 548,
    "rac": 548,
    "buil": 546,
    "lead": 546,
    "wom": 546,
    "cent": 546,
    "C ": 546,
    "Cl": 545,
    "fect": 544,
    "7 ": 541,
    "differ": 539,
    "new": 537,
    "inst": 537,
    "issu": 536,
    "requ": 536,
    "rel": 536,
    "8 ": 535,
    "wat": 534,
    "Mar": 534,
    "point": 532,
    ".\n\n\u201c": 532,
    ".\n\n\"": 531,
    "cor": 531,
    "work ": 530,
    "eb": 530,
    "alk": 529,
    "s are ": 529,
    "ce ": 529,
    "E ": 529,
    "produc": 528,
    "\u2018": 527,
    "ask": 527,
    "ll ": 524,
    "200": 523,
    "ub": 523,
    "\\": 522,
    "will be ": 522,
    "New ": 522,
    "Br": 522,
    "*": 521,
    "You ": 521,
    "ble ": 521,
    "stor": 521,
    "det": 519,
    "cc": 519,
    "vis": 518,
    "soc": 516,
    "ish ": 514,
    "sol": 514,
    "both": 513,
    "back ": 512,
    "ime ": 511,
    "develop": 508,
    "seas": 507,
    "fil": 507,
    "still ": 506,
    "right": 506,
    "a t": 506,
    "beli": 505,
    "ed that ": 505,
    "er of ": 503,
    "grou": 502,
    "fact": 502,
    "prot": 501,
    " these ": 501,
    "much ": 501,
    "dur": 501,
    "ber": 499,
    "unt": 498,
    "show": 497,
    "sul": 497,
    "sm": 497,
    "gre": 497,
    "bo": 497,
    "hand": 496,
    "e.": 496,
    "ash": 495,
    ".\n\nA": 494,
    "in a ": 494,
    "down": 494,
    ". M": 493,
    "ff": 493,
    "Trum": 491,
    "cha": 490,
    ". \u201c": 489,
    "did ": 489,
    "It": 489,
    "as the ": 487,
    "ning ": 487,
    "ustr": 486,
    ". He ": 484,
    ". It ": 484,
    "spec": 484,
    "happ": 484,
    "stand": 484,
    "ollow": 483,
    "ari": 483,
    "ide ": 482,
    "how": 482,
    "ful": 482,
    "syst": 480,
    " those ": 480,
    "ually ": 480,
    "ivers": 480,
    ", which ": 479,
    "chool": 478,
    "ition ": 478,
    "oper": 477,
    "]\n\n": 477,
    "peri": 476,
    "n't ": 475,
    "pow": 474,
    "impl": 473,
    "has been ": 472,
    "ros": 472,
    "ily ": 471,
    "son ": 470,
    "T ": 470,
    "En": 470,
    "cour": 469,
    "polit": 468,
    "ident ": 468,
    "me ": 468,
    "fam": 468,
    "ember ": 467,
    "see ": 467,
    "expl": 467,
    "dem": 467,
    "ct": 466,
    "ific": 465,
    "made ": 464,
    ")\n\n": 463,
    "@": 371,
    "Z": 358,
    "&": 340,
    "\u2026": 327,
    "+": 285,
    "#": 270,
    "X": 265,
    "}": 243,
    "{": 242,
    "\u2022": 200,
    "\u0627": 177,
    ">": 160,
    "^": 154,
    "\u00e9": 121,
    "\u0644": 92,
    "\u00e1": 80,
    "\u0646": 79,
    "\u0645": 75,
    "\uc774": 72,
    "<": 64,
    "\ub2e4": 58,
    "~": 55,
    "\u0648": 55,
    "\u062a": 54,
    "\u064a": 51
}